brax/__init__.py
brax/actuator.py
brax/actuator_test.py
brax/base.py
brax/base_test.py
brax/com.py
brax/com_test.py
brax/contact.py
brax/contact_test.py
brax/fluid.py
brax/fluid_test.py
brax/kinematics.py
brax/kinematics_test.py
brax/math.py
brax/math_test.py
brax/scan.py
brax/scan_test.py
brax/test_utils.py
brax/envs/__init__.py
brax/envs/ant.py
brax/envs/base.py
brax/envs/env_test.py
brax/envs/fast.py
brax/envs/half_cheetah.py
brax/envs/hopper.py
brax/envs/humanoid.py
brax/envs/humanoidstandup.py
brax/envs/inverted_double_pendulum.py
brax/envs/inverted_pendulum.py
brax/envs/pusher.py
brax/envs/reacher.py
brax/envs/swimmer.py
brax/envs/walker2d.py
brax/envs/assets/ant.xml
brax/envs/assets/half_cheetah.xml
brax/envs/assets/hopper.xml
brax/envs/assets/humanoid.xml
brax/envs/assets/humanoidstandup.xml
brax/envs/assets/inverted_double_pendulum.xml
brax/envs/assets/inverted_pendulum.xml
brax/envs/assets/pusher.xml
brax/envs/assets/reacher.xml
brax/envs/assets/swimmer.xml
brax/envs/assets/walker2d.xml
brax/envs/wrappers/__init__.py
brax/envs/wrappers/dm_env.py
brax/envs/wrappers/dm_env_test.py
brax/envs/wrappers/gym.py
brax/envs/wrappers/gym_test.py
brax/envs/wrappers/torch.py
brax/envs/wrappers/training.py
brax/envs/wrappers/training_test.py
brax/experimental/__init__.py
brax/experimental/barkour/README.md
brax/experimental/barkour/__init__.py
brax/experimental/barkour/score_barkour.py
brax/experimental/barkour/tutorial.ipynb
brax/generalized/__init__.py
brax/generalized/base.py
brax/generalized/constraint.py
brax/generalized/constraint_test.py
brax/generalized/dynamics.py
brax/generalized/dynamics_test.py
brax/generalized/integrator.py
brax/generalized/mass.py
brax/generalized/mass_test.py
brax/generalized/perf_test.py
brax/generalized/pipeline.py
brax/generalized/pipeline_test.py
brax/io/__init__.py
brax/io/html.py
brax/io/image.py
brax/io/json.py
brax/io/json_test.py
brax/io/metrics.py
brax/io/mjcf.py
brax/io/mjcf_test.py
brax/io/model.py
brax/io/torch.py
brax-0.14.0.dist-info/METADATA
brax-0.14.0.dist-info/WHEEL
brax-0.14.0.dist-info/licenses/LICENSE
brax-0.14.0.dist-info/RECORD
