Metadata-Version: 2.4
Name: brax
Version: 0.14.0
Summary: A differentiable physics engine written in JAX.
Project-URL: Homepage, http://github.com/google/brax
Author-email: Brax Authors <no-reply@google.com>
License:                                  Apache License
License-File: LICENSE
Keywords: JAX,physics,reinforcement learning,rigidbody
Classifier: Development Status :: 4 - Beta
Classifier: Intended Audience :: Developers
Classifier: Intended Audience :: Science/Research
Classifier: License :: OSI Approved :: Apache Software License
Classifier: Programming Language :: Python
Classifier: Programming Language :: Python :: 3.10
Classifier: Programming Language :: Python :: 3.11
Classifier: Programming Language :: Python :: 3.12
Classifier: Topic :: Scientific/Engineering :: Artificial Intelligence
Requires-Python: >=3.10
Requires-Dist: absl-py
Requires-Dist: dataclasses; python_version < '3.7'
Requires-Dist: etils
Requires-Dist: flask
Requires-Dist: flask-cors
Requires-Dist: flax
Requires-Dist: jax>=0.4.6
Requires-Dist: jaxlib>=0.4.6
Requires-Dist: jaxopt
Requires-Dist: jinja2
Requires-Dist: ml-collections
Requires-Dist: mujoco
Requires-Dist: mujoco-mjx
Requires-Dist: numpy
Requires-Dist: optax
Requires-Dist: orbax-checkpoint>=0.11.22
Requires-Dist: pillow
Requires-Dist: scipy
Requires-Dist: tensorboardx
Requires-Dist: trimesh
Requires-Dist: typing-extensions
Provides-Extra: develop
Requires-Dist: dm-env; extra == 'develop'
Requires-Dist: gym; extra == 'develop'
Requires-Dist: pytest; extra == 'develop'
Requires-Dist: transforms3d; extra == 'develop'
